tol_colors/__init__.py
tol_colors/__main__.py
tol_colors/colors.json
tol_colors/py.typed
tol_colors-2.0.0.post1.dist-info/licenses/LICENSE
tol_colors-2.0.0.post1.dist-info/METADATA
tol_colors-2.0.0.post1.dist-info/WHEEL
tol_colors-2.0.0.post1.dist-info/top_level.txt
tol_colors-2.0.0.post1.dist-info/RECORD
