Metadata-Version: 2.4
Name: tol_colors
Version: 2.0.0.post1
Summary: Color schemes for lines and maps, color-blind safe
Author: Paul Tol
Author-email: Clément Haëck <clement.haeck@posteo.net>
Maintainer-email: Clément Haëck <clement.haeck@posteo.net>
License-Expression: BSD-3-Clause
Project-URL: Source, https://github.com/Descanonge/tol_colors
Project-URL: Documentation, https://tol-colors.readthedocs.io
Keywords: visualization,colorsets,colormaps,colorblind
Classifier: Programming Language :: Python :: 3
Classifier: Operating System :: OS Independent
Classifier: Development Status :: 5 - Production/Stable
Classifier: Intended Audience :: Science/Research
Classifier: Topic :: Scientific/Engineering :: Visualization
Requires-Python: >=3.9
License-File: LICENSE
Requires-Dist: numpy
Requires-Dist: matplotlib
Provides-Extra: dev
Requires-Dist: ruff; extra == "dev"
Requires-Dist: mypy>=1.5; extra == "dev"
Requires-Dist: pytest>=7.4; extra == "dev"
Provides-Extra: docs
Requires-Dist: sphinx==8.2.*; extra == "docs"
Requires-Dist: pydata-sphinx-theme==0.15.*; extra == "docs"
Requires-Dist: colorspacious; extra == "docs"
Requires-Dist: viscm; extra == "docs"
Requires-Dist: PyQt5; extra == "docs"
Provides-Extra: tests
Requires-Dist: pytest>=7.4; extra == "tests"
Dynamic: license-file
